<?xml version="1.0"?>
<runHistory script="Cordinates">
 <run>
  <RunDate>2017-12-05 10:34:23.119 -0600</RunDate>
  <Status>Success</Status>
  <Duration>0.360000</Duration>
  <Errors>0</Errors>
  <Warnings>0</Warnings>
  <Exceptions>0</Exceptions>
  <Successes>1</Successes>
  <LogFile>20171205_103423.119/LogFile.txt</LogFile>
  <ReturnValue></ReturnValue>
  <ErrorMessage></ErrorMessage>
 </run>
 <run>
  <RunDate>2017-12-05 10:46:25.443 -0600</RunDate>
  <Status>Running</Status>
  <Duration>0.000000</Duration>
  <Errors></Errors>
  <Warnings></Warnings>
  <Exceptions></Exceptions>
  <Successes></Successes>
  <LogFile>20171205_104625.443/LogFile.txt</LogFile>
  <ReturnValue></ReturnValue>
  <ErrorMessage></ErrorMessage>
 </run>
 <run>
  <RunDate>2017-12-05 10:46:44.739 -0600</RunDate>
  <Status>Running</Status>
  <Duration>0.000000</Duration>
  <Errors></Errors>
  <Warnings></Warnings>
  <Exceptions></Exceptions>
  <Successes></Successes>
  <LogFile>20171205_104644.739/LogFile.txt</LogFile>
  <ReturnValue></ReturnValue>
  <ErrorMessage></ErrorMessage>
 </run>
 <run>
  <RunDate>2017-12-05 10:47:20.240 -0600</RunDate>
  <Status>Success</Status>
  <Duration>1.035000</Duration>
  <Errors>0</Errors>
  <Warnings>0</Warnings>
  <Exceptions>0</Exceptions>
  <Successes>1</Successes>
  <LogFile>20171205_104720.240/LogFile.txt</LogFile>
  <ReturnValue></ReturnValue>
  <ErrorMessage></ErrorMessage>
 </run>
</runHistory>
